MagiSlack/__init__.py
MagiSlack/__main__.py
MagiSlack/io/MagiIO.py
MagiSlack/io/__init__.py
MagiSlack/module/MagiModule.py
MagiSlack/module/__init__.py
MagiSlack-0.1.1.dist-info/LICENSE
MagiSlack-0.1.1.dist-info/METADATA
MagiSlack-0.1.1.dist-info/WHEEL
MagiSlack-0.1.1.dist-info/top_level.txt
MagiSlack-0.1.1.dist-info/RECORD
