Metadata-Version: 2.1
Name: MagiSlack
Version: 0.1.1
Summary: For a make easy and quick command-respond chat bot
Home-page: https://github.com/riemannulus/MagiSlack
Author: Lee, Suho
Author-email: riemannulus@hitagi.moe
License: UNKNOWN
Platform: UNKNOWN
Classifier: Programming Language :: Python :: 3.7
Classifier: License :: OSI Approved :: MIT License
Classifier: Operating System :: OS Independent
Requires-Dist: slackclient
